{
    "key": "group_6089d6189b18e",
    "title": "Author information",
    "fields": [
        {
            "key": "field_6089d62743512",
            "label": "Name",
            "name": "uds_news_author_name",
            "type": "text",
            "instructions": "",
            "required": 0,
            "conditional_logic": 0,
            "wrapper": {
                "width": "",
                "class": "",
                "id": ""
            },
            "default_value": "",
            "placeholder": "",
            "prepend": "",
            "append": "",
            "maxlength": ""
        },
        {
            "key": "field_6089d71d4de0f",
            "label": "Title",
            "name": "uds_news_author_title",
            "type": "text",
            "instructions": "",
            "required": 0,
            "conditional_logic": 0,
            "wrapper": {
                "width": "",
                "class": "",
                "id": ""
            },
            "default_value": "",
            "placeholder": "",
            "prepend": "",
            "append": "",
            "maxlength": ""
        },
        {
            "key": "field_6089d66b43513",
            "label": "Email",
            "name": "uds_news_author_email",
            "type": "email",
            "instructions": "",
            "required": 0,
            "conditional_logic": 0,
            "wrapper": {
                "width": "",
                "class": "",
                "id": ""
            },
            "default_value": "",
            "placeholder": "",
            "prepend": "",
            "append": ""
        },
        {
            "key": "field_6089d67c43514",
            "label": "Phone",
            "name": "uds_news_author_phone",
            "type": "number",
            "instructions": "Numbers only. Example: 4805551212",
            "required": 0,
            "conditional_logic": 0,
            "wrapper": {
                "width": "",
                "class": "",
                "id": ""
            },
            "default_value": "",
            "placeholder": "",
            "prepend": "",
            "append": "",
            "min": "",
            "max": "",
            "step": ""
        }
    ],
    "location": [
        [
            {
                "param": "post_type",
                "operator": "==",
                "value": "post"
            }
        ]
    ],
    "menu_order": 10,
    "position": "side",
    "style": "default",
    "label_placement": "top",
    "instruction_placement": "field",
    "hide_on_screen": [
        "author"
    ],
    "active": true,
    "description": "Article author fields for ASU News posts",
    "modified": 1631209207
}